bluebees/__init__.py
bluebees/__main__.py
bluebees/client/__init__.py
bluebees/client/data_paths.py
bluebees/client/application/__init__.py
bluebees/client/application/application.py
bluebees/client/application/application_data.py
bluebees/client/application/commands/__init__.py
bluebees/client/application/commands/info.py
bluebees/client/application/commands/list.py
bluebees/client/application/commands/new.py
bluebees/client/core/__init__.py
bluebees/client/core/core.py
bluebees/client/core/dongle.py
bluebees/client/core/commands/__init__.py
bluebees/client/core/commands/run.py
bluebees/client/device/__init__.py
bluebees/client/device/device.py
bluebees/client/device/list_devices.py
bluebees/client/device/commands/__init__.py
bluebees/client/device/commands/list.py
bluebees/client/mesh_layers/__init__.py
bluebees/client/mesh_layers/access_layer.py
bluebees/client/mesh_layers/address.py
bluebees/client/mesh_layers/element.py
bluebees/client/mesh_layers/mesh_context.py
bluebees/client/mesh_layers/network_layer.py
bluebees/client/mesh_layers/transport_layer.py
bluebees/client/network/__init__.py
bluebees/client/network/network.py
bluebees/client/network/network_data.py
bluebees/client/network/commands/__init__.py
bluebees/client/network/commands/info.py
bluebees/client/network/commands/list.py
bluebees/client/network/commands/new.py
bluebees/client/node/__init__.py
bluebees/client/node/group_data.py
bluebees/client/node/node.py
bluebees/client/node/node_data.py
bluebees/client/node/provisioner.py
bluebees/client/node/commands/__init__.py
bluebees/client/node/commands/add_appkey.py
bluebees/client/node/commands/config.py
bluebees/client/node/commands/info.py
bluebees/client/node/commands/list.py
bluebees/client/node/commands/new.py
bluebees/client/node/commands/req.py
bluebees/client/node/commands/send.py
bluebees/common/__init__.py
bluebees/common/asyncio_fixup.py
bluebees/common/broker.py
bluebees/common/client.py
bluebees-1.0.10.dist-info/DESCRIPTION.rst
bluebees-1.0.10.dist-info/METADATA
bluebees-1.0.10.dist-info/RECORD
bluebees-1.0.10.dist-info/WHEEL
bluebees-1.0.10.dist-info/entry_points.txt
bluebees-1.0.10.dist-info/metadata.json
bluebees-1.0.10.dist-info/top_level.txt
