Metadata-Version: 2.0
Name: bluebees
Version: 1.0.10
Summary: Bluetooth Mesh Config Tools
Home-page: https://github.com/matheuswhite/bluebees
Author: Matheus White
Author-email: tenoriomatheus0@gmail.com
License: GPL3
Platform: UNKNOWN
Classifier: Intended Audience :: Developers
Classifier: License :: OSI Approved :: GNU General Public License v3 or later (GPLv3+)
Classifier: Programming Language :: Python :: 3.7
Requires-Dist: pycryptodome (==3.7.3)
Requires-Dist: termcolor (==1.1.0)
Requires-Dist: pyserial (==3.4)
Requires-Dist: ecdsa (==0.13)
Requires-Dist: ruamel.yaml (==0.15.94)
Requires-Dist: pyzmq (==18.0.1)
Requires-Dist: asyncserial (==0.1.0)
Requires-Dist: pytest (==4.5.0)
Requires-Dist: codecov (==2.0.15)
Requires-Dist: pytest-cov (==2.7.1)
Requires-Dist: click (==7.0)
Requires-Dist: tqdm (==4.32.1)
Requires-Dist: dataclasses (==0.6)
